ganessa/OpenFileMMI.py
ganessa/__init__.py
ganessa/_epanet2.cp38-win32.pyd
ganessa/_epanet22.cp38-win32.pyd
ganessa/_getdll.py
ganessa/_prot.cp38-win32.pyd
ganessa/_pygan_th.cp38-win32.pyd
ganessa/_pygan_th2016.cp38-win32.pyd
ganessa/_pygan_th2016b.cp38-win32.pyd
ganessa/_pygan_th2017.cp38-win32.pyd
ganessa/_pygan_th2018.cp38-win32.pyd
ganessa/_pygan_th2021.cp38-win32.pyd
ganessa/_pygan_th2025.cp38-win32.pyd
ganessa/_pygansim.cp38-win32.pyd
ganessa/_pygansim2016.cp38-win32.pyd
ganessa/_pygansim2016a.cp38-win32.pyd
ganessa/_pygansim2016b.cp38-win32.pyd
ganessa/_pygansim2017.cp38-win32.pyd
ganessa/_pygansim2017b.cp38-win32.pyd
ganessa/_pygansim2018.cp38-win32.pyd
ganessa/_pygansim2018b.cp38-win32.pyd
ganessa/_pygansim2020.cp38-win32.pyd
ganessa/_pygansim2021.cp38-win32.pyd
ganessa/_pygansim2022.cp38-win32.pyd
ganessa/_pygansim2023.cp38-win32.pyd
ganessa/_pygansim2025.cp38-win32.pyd
ganessa/_pygansim_alt.cp38-win32.pyd
ganessa/_pyganutl.cp38-win32.pyd
ganessa/core.py
ganessa/core_sim.py
ganessa/core_th.py
ganessa/en2emu.py
ganessa/epanet2.py
ganessa/epanet22.py
ganessa/geojsonfile.py
ganessa/midfile.py
ganessa/multithread.py
ganessa/owa_epanet22.py
ganessa/parallel.py
ganessa/plot.py
ganessa/proj.py
ganessa/prot.py
ganessa/pyGanessa.css
ganessa/pyGanessa.html
ganessa/sim.py
ganessa/sort.py
ganessa/th.py
ganessa/util.py
ganessa-2.5.4.dist-info/METADATA
ganessa-2.5.4.dist-info/WHEEL
ganessa-2.5.4.dist-info/top_level.txt
ganessa-2.5.4.dist-info/RECORD
